ffconcat/__init__.py
ffconcat/ffconcat.py
ffconcat-0.1.1.dist-info/entry_points.txt
ffconcat-0.1.1.dist-info/LICENSE
ffconcat-0.1.1.dist-info/WHEEL
ffconcat-0.1.1.dist-info/METADATA
ffconcat-0.1.1.dist-info/RECORD
