Metadata-Version: 2.1
Name: ffconcat
Version: 0.1.1
Summary: Easily concat videos with FFmpeg from Python
License: MIT
Author: Alyetama
Author-email: malyetama@pm.me
Requires-Python: >=3.6,<4.0
Classifier: License :: OSI Approved :: MIT License
Classifier: Programming Language :: Python :: 3
Classifier: Programming Language :: Python :: 3.10
Classifier: Programming Language :: Python :: 3.6
Classifier: Programming Language :: Python :: 3.7
Classifier: Programming Language :: Python :: 3.8
Classifier: Programming Language :: Python :: 3.9
Requires-Dist: ffmpeg (>=1.4,<2.0)
